qwertyai/__init__.py
qwertyai/qwertyai.py
qwertyai-0.1.0.dist-info/METADATA
qwertyai-0.1.0.dist-info/WHEEL
qwertyai-0.1.0.dist-info/top_level.txt
qwertyai-0.1.0.dist-info/RECORD
